{
  "id": "FAM_MERTENSIIDAE",
  "name": "Mertensiidae",
  "rank": "FAMILY",
  "commonName": "Mertensiid comb jellies",
  "children": [
    {
      "id": "GENUS_CHARISTEPHANE",
      "name": "Charistephane",
      "rank": "GENUS",
      "description": "Charistephane — a genus of mertensiid comb jellies in the family Mertensiidae.",
      "lineage": "Charistephane",
      "children": [
        {
          "id": "CHARISTEPHANE_FUGIENS",
          "name": "Charistephane fugiens",
          "rank": "SPECIES",
          "commonName": "Charistephane Fugiens",
          "lineage": "Charistephane",
          "continents": [],
          "subspeciesCount": 0,
          "description": "Charistephane fugiens — a species in the genus Charistephane, family Mertensiidae. Also known as mertensiid comb jellies.",
          "sourcedFrom": "generated"
        }
      ]
    },
    {
      "id": "GENUS_MERTENSIA",
      "name": "Mertensia",
      "rank": "GENUS",
      "description": "Mertensia — a genus of mertensiid comb jellies in the family Mertensiidae.",
      "lineage": "Mertensia",
      "children": [
        {
          "id": "MERTENSIA_OVUM",
          "name": "Mertensia ovum",
          "rank": "SPECIES",
          "commonName": "Mertensia Ovum",
          "lineage": "Mertensia",
          "continents": [],
          "subspeciesCount": 0,
          "description": "Mertensia ovum — a species in the genus Mertensia, family Mertensiidae. Also known as mertensiid comb jellies.",
          "sourcedFrom": "generated"
        }
      ]
    },
    {
      "id": "GENUS_CALLIANIRA",
      "name": "Callianira",
      "rank": "GENUS",
      "description": "Callianira — a genus of mertensiid comb jellies in the family Mertensiidae.",
      "lineage": "Callianira",
      "children": [
        {
          "id": "CALLIANIRA_ANTARCTICA",
          "name": "Callianira antarctica",
          "rank": "SPECIES",
          "commonName": "Callianira Antarctica",
          "lineage": "Callianira",
          "continents": [],
          "subspeciesCount": 0,
          "description": "Callianira antarctica — a species in the genus Callianira, family Mertensiidae. Also known as mertensiid comb jellies.",
          "sourcedFrom": "generated"
        },
        {
          "id": "CALLIANIRA_BIALATA",
          "name": "Callianira bialata",
          "rank": "SPECIES",
          "commonName": "Callianira Bialata",
          "lineage": "Callianira",
          "continents": [],
          "subspeciesCount": 0,
          "description": "Callianira bialata — a species in the genus Callianira, family Mertensiidae. Also known as mertensiid comb jellies.",
          "sourcedFrom": "generated"
        },
        {
          "id": "CALLIANIRA_COMPRESSA",
          "name": "Callianira compressa",
          "rank": "SPECIES",
          "commonName": "Callianira Compressa",
          "lineage": "Callianira",
          "continents": [],
          "subspeciesCount": 0,
          "description": "Callianira compressa — a species in the genus Callianira, family Mertensiidae. Also known as mertensiid comb jellies.",
          "sourcedFrom": "generated"
        },
        {
          "id": "CALLIANIRA_CRISTATA",
          "name": "Callianira cristata",
          "rank": "SPECIES",
          "commonName": "Callianira Cristata",
          "lineage": "Callianira",
          "continents": [],
          "subspeciesCount": 0,
          "description": "Callianira cristata — a species in the genus Callianira, family Mertensiidae. Also known as mertensiid comb jellies.",
          "sourcedFrom": "generated"
        },
        {
          "id": "CALLIANIRA_DIPLOPTERA",
          "name": "Callianira diploptera",
          "rank": "SPECIES",
          "commonName": "Callianira Diploptera",
          "lineage": "Callianira",
          "continents": [],
          "subspeciesCount": 0,
          "description": "Callianira diploptera — a species in the genus Callianira, family Mertensiidae. Also known as mertensiid comb jellies.",
          "sourcedFrom": "generated"
        },
        {
          "id": "CALLIANIRA_FICALBI",
          "name": "Callianira ficalbi",
          "rank": "SPECIES",
          "commonName": "Callianira Ficalbi",
          "lineage": "Callianira",
          "continents": [],
          "subspeciesCount": 0,
          "description": "Callianira ficalbi — a species in the genus Callianira, family Mertensiidae. Also known as mertensiid comb jellies.",
          "sourcedFrom": "generated"
        }
      ]
    }
  ]
}
