{
  "id": "FAM_TRICHOCERCIDAE",
  "name": "Trichocercidae",
  "rank": "FAMILY",
  "commonName": "Trichocercidae",
  "children": [
    {
      "id": "GENUS_ELOSA",
      "name": "Elosa",
      "rank": "GENUS",
      "description": "Elosa — a genus of eurotatorias.",
      "lineage": "Elosa",
      "children": [
        {
          "id": "SP_ELOSA_SPINIFERA_WISZNIEWSKI_1932",
          "name": "Elosa spinifera Wiszniewski, 1932",
          "rank": "SPECIES",
          "commonName": "Elosa Spinifera Wiszniewski, 1932",
          "lineage": "Elosa",
          "subspeciesCount": 0,
          "description": "Elosa spinifera Wiszniewski, 1932 — a eurotatoria species in the genus Elosa.",
          "sourcedFrom": "generated"
        },
        {
          "id": "SP_ELOSA_WORRALLII_LORD_1891",
          "name": "Elosa worrallii Lord, 1891",
          "rank": "SPECIES",
          "commonName": "Elosa Worrallii Lord, 1891",
          "lineage": "Elosa",
          "subspeciesCount": 0,
          "description": "Elosa worrallii Lord, 1891 — a eurotatoria species in the genus Elosa.",
          "sourcedFrom": "generated"
        }
      ]
    },
    {
      "id": "GENUS_ASCOMORPHELLA",
      "name": "Ascomorphella",
      "rank": "GENUS",
      "description": "Ascomorphella — a genus of eurotatorias.",
      "lineage": "Ascomorphella",
      "children": [
        {
          "id": "SP_ASCOMORPHELLA_VOLVOCICOLA",
          "name": "Ascomorphella volvocicola",
          "rank": "SPECIES",
          "commonName": "Ascomorphella Volvocicola",
          "lineage": "Ascomorphella",
          "subspeciesCount": 0,
          "description": "Ascomorphella volvocicola — a eurotatoria species in the genus Ascomorphella.",
          "sourcedFrom": "generated"
        }
      ]
    },
    {
      "id": "GENUS_TRICHOCERCA",
      "name": "Trichocerca",
      "rank": "GENUS",
      "description": "Trichocerca — a genus of eurotatorias.",
      "lineage": "Trichocerca",
      "children": [
        {
          "id": "SP_TRICHOCERCA_ABILIOI_SEGERS_SARMA_1993",
          "name": "Trichocerca abilioi Segers & Sarma, 1993",
          "rank": "SPECIES",
          "commonName": "Trichocerca Abilioi Segers & Sarma, 1993",
          "lineage": "Trichocerca",
          "subspeciesCount": 0,
          "description": "Trichocerca abilioi Segers & Sarma, 1993 — a eurotatoria species in the genus Trichocerca.",
          "sourcedFrom": "generated"
        },
        {
          "id": "SP_TRICHOCERCA_AGNATHA_WULFERT_1939",
          "name": "Trichocerca agnatha Wulfert, 1939",
          "rank": "SPECIES",
          "commonName": "Trichocerca Agnatha Wulfert, 1939",
          "lineage": "Trichocerca",
          "subspeciesCount": 0,
          "description": "Trichocerca agnatha Wulfert, 1939 — a eurotatoria species in the genus Trichocerca.",
          "sourcedFrom": "generated"
        },
        {
          "id": "SP_TRICHOCERCA_ANTILOPAEA",
          "name": "Trichocerca antilopaea",
          "rank": "SPECIES",
          "commonName": "Trichocerca Antilopaea",
          "lineage": "Trichocerca",
          "subspeciesCount": 0,
          "description": "Trichocerca antilopaea — a eurotatoria species in the genus Trichocerca.",
          "sourcedFrom": "generated"
        },
        {
          "id": "SP_TRICHOCERCA_ARTMANNI",
          "name": "Trichocerca artmanni",
          "rank": "SPECIES",
          "commonName": "Trichocerca Artmanni",
          "lineage": "Trichocerca",
          "subspeciesCount": 0,
          "description": "Trichocerca artmanni — a eurotatoria species in the genus Trichocerca.",
          "sourcedFrom": "generated"
        },
        {
          "id": "SP_TRICHOCERCA_BAMBEKEI",
          "name": "Trichocerca bambekei",
          "rank": "SPECIES",
          "commonName": "Trichocerca Bambekei",
          "lineage": "Trichocerca",
          "subspeciesCount": 0,
          "description": "Trichocerca bambekei — a eurotatoria species in the genus Trichocerca.",
          "sourcedFrom": "generated"
        },
        {
          "id": "SP_TRICHOCERCA_BARSICA",
          "name": "Trichocerca barsica",
          "rank": "SPECIES",
          "commonName": "Trichocerca Barsica",
          "lineage": "Trichocerca",
          "subspeciesCount": 0,
          "description": "Trichocerca barsica — a eurotatoria species in the genus Trichocerca.",
          "sourcedFrom": "generated"
        },
        {
          "id": "SP_TRICHOCERCA_BAUTHIEMENSIS",
          "name": "Trichocerca bauthiemensis",
          "rank": "SPECIES",
          "commonName": "Trichocerca Bauthiemensis",
          "lineage": "Trichocerca",
          "subspeciesCount": 0,
          "description": "Trichocerca bauthiemensis — a eurotatoria species in the genus Trichocerca.",
          "sourcedFrom": "generated"
        },
        {
          "id": "SP_TRICHOCERCA_BICRISTATA",
          "name": "Trichocerca bicristata",
          "rank": "SPECIES",
          "commonName": "Trichocerca Bicristata",
          "lineage": "Trichocerca",
          "subspeciesCount": 0,
          "description": "Trichocerca bicristata — a eurotatoria species in the genus Trichocerca.",
          "sourcedFrom": "generated"
        },
        {
          "id": "SP_TRICHOCERCA_BICURVICORNIS",
          "name": "Trichocerca bicurvicornis",
          "rank": "SPECIES",
          "commonName": "Trichocerca Bicurvicornis",
          "lineage": "Trichocerca",
          "subspeciesCount": 0,
          "description": "Trichocerca bicurvicornis — a eurotatoria species in the genus Trichocerca.",
          "sourcedFrom": "generated"
        },
        {
          "id": "SP_TRICHOCERCA_BICUSPES",
          "name": "Trichocerca bicuspes",
          "rank": "SPECIES",
          "commonName": "Trichocerca Bicuspes",
          "lineage": "Trichocerca",
          "subspeciesCount": 0,
          "description": "Trichocerca bicuspes — a eurotatoria species in the genus Trichocerca.",
          "sourcedFrom": "generated"
        },
        {
          "id": "SP_TRICHOCERCA_BIDENS",
          "name": "Trichocerca bidens",
          "rank": "SPECIES",
          "commonName": "Trichocerca Bidens",
          "lineage": "Trichocerca",
          "subspeciesCount": 0,
          "description": "Trichocerca bidens — a eurotatoria species in the genus Trichocerca.",
          "sourcedFrom": "generated"
        },
        {
          "id": "SP_TRICHOCERCA_BILUNARIS_BLAINVILLE_1830",
          "name": "Trichocerca bilunaris Blainville, 1830",
          "rank": "SPECIES",
          "commonName": "Trichocerca Bilunaris Blainville, 1830",
          "lineage": "Trichocerca",
          "subspeciesCount": 0,
          "description": "Trichocerca bilunaris Blainville, 1830 — a eurotatoria species in the genus Trichocerca.",
          "sourcedFrom": "generated"
        },
        {
          "id": "SP_TRICHOCERCA_BRACHYDACTYLA",
          "name": "Trichocerca brachydactyla",
          "rank": "SPECIES",
          "commonName": "Trichocerca Brachydactyla",
          "lineage": "Trichocerca",
          "subspeciesCount": 0,
          "description": "Trichocerca brachydactyla — a eurotatoria species in the genus Trichocerca.",
          "sourcedFrom": "generated"
        },
        {
          "id": "SP_TRICHOCERCA_BRACHYURA",
          "name": "Trichocerca brachyura",
          "rank": "SPECIES",
          "commonName": "Trichocerca Brachyura",
          "lineage": "Trichocerca",
          "subspeciesCount": 0,
          "description": "Trichocerca brachyura — a eurotatoria species in the genus Trichocerca.",
          "sourcedFrom": "generated"
        },
        {
          "id": "SP_TRICHOCERCA_BRAZILIENSIS",
          "name": "Trichocerca braziliensis",
          "rank": "SPECIES",
          "commonName": "Trichocerca Braziliensis",
          "lineage": "Trichocerca",
          "subspeciesCount": 0,
          "description": "Trichocerca braziliensis — a eurotatoria species in the genus Trichocerca.",
          "sourcedFrom": "generated"
        },
        {
          "id": "SP_TRICHOCERCA_BREVIDACTYLA",
          "name": "Trichocerca brevidactyla",
          "rank": "SPECIES",
          "commonName": "Trichocerca Brevidactyla",
          "lineage": "Trichocerca",
          "subspeciesCount": 0,
          "description": "Trichocerca brevidactyla — a eurotatoria species in the genus Trichocerca.",
          "sourcedFrom": "generated"
        },
        {
          "id": "SP_TRICHOCERCA_BREVISTYLA",
          "name": "Trichocerca brevistyla",
          "rank": "SPECIES",
          "commonName": "Trichocerca Brevistyla",
          "lineage": "Trichocerca",
          "subspeciesCount": 0,
          "description": "Trichocerca brevistyla — a eurotatoria species in the genus Trichocerca.",
          "sourcedFrom": "generated"
        },
        {
          "id": "SP_TRICHOCERCA_CALYPTA",
          "name": "Trichocerca calypta",
          "rank": "SPECIES",
          "commonName": "Trichocerca Calypta",
          "lineage": "Trichocerca",
          "subspeciesCount": 0,
          "description": "Trichocerca calypta — a eurotatoria species in the genus Trichocerca.",
          "sourcedFrom": "generated"
        },
        {
          "id": "SP_TRICHOCERCA_CAPUCINA",
          "name": "Trichocerca capucina",
          "rank": "SPECIES",
          "commonName": "Trichocerca Capucina",
          "lineage": "Trichocerca",
          "subspeciesCount": 0,
          "description": "Trichocerca capucina — a eurotatoria species in the genus Trichocerca.",
          "sourcedFrom": "generated"
        },
        {
          "id": "SP_TRICHOCERCA_CASPICA",
          "name": "Trichocerca caspica",
          "rank": "SPECIES",
          "commonName": "Trichocerca Caspica",
          "lineage": "Trichocerca",
          "subspeciesCount": 0,
          "description": "Trichocerca caspica — a eurotatoria species in the genus Trichocerca.",
          "sourcedFrom": "generated"
        },
        {
          "id": "SP_TRICHOCERCA_CATELLUS",
          "name": "Trichocerca catellus",
          "rank": "SPECIES",
          "commonName": "Trichocerca Catellus",
          "lineage": "Trichocerca",
          "subspeciesCount": 0,
          "description": "Trichocerca catellus — a eurotatoria species in the genus Trichocerca.",
          "sourcedFrom": "generated"
        },
        {
          "id": "SP_TRICHOCERCA_CAVIA",
          "name": "Trichocerca cavia",
          "rank": "SPECIES",
          "commonName": "Trichocerca Cavia",
          "lineage": "Trichocerca",
          "subspeciesCount": 0,
          "description": "Trichocerca cavia — a eurotatoria species in the genus Trichocerca.",
          "sourcedFrom": "generated"
        },
        {
          "id": "SP_TRICHOCERCA_CHATTONI",
          "name": "Trichocerca chattoni",
          "rank": "SPECIES",
          "commonName": "Trichocerca Chattoni",
          "lineage": "Trichocerca",
          "subspeciesCount": 0,
          "description": "Trichocerca chattoni — a eurotatoria species in the genus Trichocerca.",
          "sourcedFrom": "generated"
        },
        {
          "id": "SP_TRICHOCERCA_CIMOLIA",
          "name": "Trichocerca cimolia",
          "rank": "SPECIES",
          "commonName": "Trichocerca Cimolia",
          "lineage": "Trichocerca",
          "subspeciesCount": 0,
          "description": "Trichocerca cimolia — a eurotatoria species in the genus Trichocerca.",
          "sourcedFrom": "generated"
        },
        {
          "id": "SP_TRICHOCERCA_COLLARIS",
          "name": "Trichocerca collaris",
          "rank": "SPECIES",
          "commonName": "Trichocerca Collaris",
          "lineage": "Trichocerca",
          "subspeciesCount": 0,
          "description": "Trichocerca collaris — a eurotatoria species in the genus Trichocerca.",
          "sourcedFrom": "generated"
        },
        {
          "id": "SP_TRICHOCERCA_COMPRESSA_EDMONDSON_1938",
          "name": "Trichocerca compressa Edmondson, 1938",
          "rank": "SPECIES",
          "commonName": "Trichocerca Compressa Edmondson, 1938",
          "lineage": "Trichocerca",
          "subspeciesCount": 0,
          "description": "Trichocerca compressa Edmondson, 1938 — a eurotatoria species in the genus Trichocerca.",
          "sourcedFrom": "generated"
        },
        {
          "id": "SP_TRICHOCERCA_CRYPTODUS",
          "name": "Trichocerca cryptodus",
          "rank": "SPECIES",
          "commonName": "Trichocerca Cryptodus",
          "lineage": "Trichocerca",
          "subspeciesCount": 0,
          "description": "Trichocerca cryptodus — a eurotatoria species in the genus Trichocerca.",
          "sourcedFrom": "generated"
        },
        {
          "id": "SP_TRICHOCERCA_CUSPIDATA",
          "name": "Trichocerca cuspidata",
          "rank": "SPECIES",
          "commonName": "Trichocerca Cuspidata",
          "lineage": "Trichocerca",
          "subspeciesCount": 0,
          "description": "Trichocerca cuspidata — a eurotatoria species in the genus Trichocerca.",
          "sourcedFrom": "generated"
        },
        {
          "id": "SP_TRICHOCERCA_CYLINDRICA",
          "name": "Trichocerca cylindrica",
          "rank": "SPECIES",
          "commonName": "Trichocerca Cylindrica",
          "lineage": "Trichocerca",
          "subspeciesCount": 0,
          "description": "Trichocerca cylindrica — a eurotatoria species in the genus Trichocerca.",
          "sourcedFrom": "generated"
        },
        {
          "id": "SP_TRICHOCERCA_DIXONNUTTALLI",
          "name": "Trichocerca dixonnuttalli",
          "rank": "SPECIES",
          "commonName": "Trichocerca Dixonnuttalli",
          "lineage": "Trichocerca",
          "subspeciesCount": 0,
          "description": "Trichocerca dixonnuttalli — a eurotatoria species in the genus Trichocerca.",
          "sourcedFrom": "generated"
        },
        {
          "id": "SP_TRICHOCERCA_EDMONDSONI",
          "name": "Trichocerca edmondsoni",
          "rank": "SPECIES",
          "commonName": "Trichocerca Edmondsoni",
          "lineage": "Trichocerca",
          "subspeciesCount": 0,
          "description": "Trichocerca edmondsoni — a eurotatoria species in the genus Trichocerca.",
          "sourcedFrom": "generated"
        },
        {
          "id": "SP_TRICHOCERCA_ELONGATA",
          "name": "Trichocerca elongata",
          "rank": "SPECIES",
          "commonName": "Trichocerca Elongata",
          "lineage": "Trichocerca",
          "subspeciesCount": 0,
          "description": "Trichocerca elongata — a eurotatoria species in the genus Trichocerca.",
          "sourcedFrom": "generated"
        },
        {
          "id": "SP_TRICHOCERCA_EUODONTA",
          "name": "Trichocerca euodonta",
          "rank": "SPECIES",
          "commonName": "Trichocerca Euodonta",
          "lineage": "Trichocerca",
          "subspeciesCount": 0,
          "description": "Trichocerca euodonta — a eurotatoria species in the genus Trichocerca.",
          "sourcedFrom": "generated"
        },
        {
          "id": "SP_TRICHOCERCA_FLAGELLATA_HAUER_1937",
          "name": "Trichocerca flagellata Hauer, 1937",
          "rank": "SPECIES",
          "commonName": "Trichocerca Flagellata Hauer, 1937",
          "lineage": "Trichocerca",
          "subspeciesCount": 0,
          "description": "Trichocerca flagellata Hauer, 1937 — a eurotatoria species in the genus Trichocerca.",
          "sourcedFrom": "generated"
        },
        {
          "id": "SP_TRICHOCERCA_FLAVA",
          "name": "Trichocerca flava",
          "rank": "SPECIES",
          "commonName": "Trichocerca Flava",
          "lineage": "Trichocerca",
          "subspeciesCount": 0,
          "description": "Trichocerca flava — a eurotatoria species in the genus Trichocerca.",
          "sourcedFrom": "generated"
        },
        {
          "id": "SP_TRICHOCERCA_GILLARDI_KOSTE_1978",
          "name": "Trichocerca gillardi Koste, 1978",
          "rank": "SPECIES",
          "commonName": "Trichocerca Gillardi Koste, 1978",
          "lineage": "Trichocerca",
          "subspeciesCount": 0,
          "description": "Trichocerca gillardi Koste, 1978 — a eurotatoria species in the genus Trichocerca.",
          "sourcedFrom": "generated"
        },
        {
          "id": "SP_TRICHOCERCA_GRACILIS",
          "name": "Trichocerca gracilis",
          "rank": "SPECIES",
          "commonName": "Trichocerca Gracilis",
          "lineage": "Trichocerca",
          "subspeciesCount": 0,
          "description": "Trichocerca gracilis — a eurotatoria species in the genus Trichocerca.",
          "sourcedFrom": "generated"
        },
        {
          "id": "SP_TRICHOCERCA_HARVEYENSIS_MYERS_1942",
          "name": "Trichocerca harveyensis Myers, 1942",
          "rank": "SPECIES",
          "commonName": "Trichocerca Harveyensis Myers, 1942",
          "lineage": "Trichocerca",
          "subspeciesCount": 0,
          "description": "Trichocerca harveyensis Myers, 1942 — a eurotatoria species in the genus Trichocerca.",
          "sourcedFrom": "generated"
        },
        {
          "id": "SP_TRICHOCERCA_HELMINTHODES",
          "name": "Trichocerca helminthodes",
          "rank": "SPECIES",
          "commonName": "Trichocerca Helminthodes",
          "lineage": "Trichocerca",
          "subspeciesCount": 0,
          "description": "Trichocerca helminthodes — a eurotatoria species in the genus Trichocerca.",
          "sourcedFrom": "generated"
        },
        {
          "id": "SP_TRICHOCERCA_HETERODACTYLA",
          "name": "Trichocerca heterodactyla",
          "rank": "SPECIES",
          "commonName": "Trichocerca Heterodactyla",
          "lineage": "Trichocerca",
          "subspeciesCount": 0,
          "description": "Trichocerca heterodactyla — a eurotatoria species in the genus Trichocerca.",
          "sourcedFrom": "generated"
        },
        {
          "id": "SP_TRICHOCERCA_HOLLAERTI_DE_SMET_1990",
          "name": "Trichocerca hollaerti De Smet, 1990",
          "rank": "SPECIES",
          "commonName": "Trichocerca Hollaerti De Smet, 1990",
          "lineage": "Trichocerca",
          "subspeciesCount": 0,
          "description": "Trichocerca hollaerti De Smet, 1990 — a eurotatoria species in the genus Trichocerca.",
          "sourcedFrom": "generated"
        },
        {
          "id": "SP_TRICHOCERCA_IERNIS",
          "name": "Trichocerca iernis",
          "rank": "SPECIES",
          "commonName": "Trichocerca Iernis",
          "lineage": "Trichocerca",
          "subspeciesCount": 0,
          "description": "Trichocerca iernis — a eurotatoria species in the genus Trichocerca.",
          "sourcedFrom": "generated"
        },
        {
          "id": "SP_TRICHOCERCA_INERMIS",
          "name": "Trichocerca inermis",
          "rank": "SPECIES",
          "commonName": "Trichocerca Inermis",
          "lineage": "Trichocerca",
          "subspeciesCount": 0,
          "description": "Trichocerca inermis — a eurotatoria species in the genus Trichocerca.",
          "sourcedFrom": "generated"
        },
        {
          "id": "SP_TRICHOCERCA_INSIGNIS",
          "name": "Trichocerca insignis",
          "rank": "SPECIES",
          "commonName": "Trichocerca Insignis",
          "lineage": "Trichocerca",
          "subspeciesCount": 0,
          "description": "Trichocerca insignis — a eurotatoria species in the genus Trichocerca.",
          "sourcedFrom": "generated"
        },
        {
          "id": "SP_TRICHOCERCA_INSOLENS",
          "name": "Trichocerca insolens",
          "rank": "SPECIES",
          "commonName": "Trichocerca Insolens",
          "lineage": "Trichocerca",
          "subspeciesCount": 0,
          "description": "Trichocerca insolens — a eurotatoria species in the genus Trichocerca.",
          "sourcedFrom": "generated"
        },
        {
          "id": "SP_TRICHOCERCA_INSULANA",
          "name": "Trichocerca insulana",
          "rank": "SPECIES",
          "commonName": "Trichocerca Insulana",
          "lineage": "Trichocerca",
          "subspeciesCount": 0,
          "description": "Trichocerca insulana — a eurotatoria species in the genus Trichocerca.",
          "sourcedFrom": "generated"
        },
        {
          "id": "SP_TRICHOCERCA_INTERMEDIA",
          "name": "Trichocerca intermedia",
          "rank": "SPECIES",
          "commonName": "Trichocerca Intermedia",
          "lineage": "Trichocerca",
          "subspeciesCount": 0,
          "description": "Trichocerca intermedia — a eurotatoria species in the genus Trichocerca.",
          "sourcedFrom": "generated"
        },
        {
          "id": "SP_TRICHOCERCA_JOBLOTII_BORY_DE_ST_VINCENT_1827",
          "name": "Trichocerca joblotii Bory de St Vincent, 1827",
          "rank": "SPECIES",
          "commonName": "Trichocerca Joblotii Bory De St Vincent, 1827",
          "lineage": "Trichocerca",
          "subspeciesCount": 0,
          "description": "Trichocerca joblotii Bory de St Vincent, 1827 — a eurotatoria species in the genus Trichocerca.",
          "sourcedFrom": "generated"
        },
        {
          "id": "SP_TRICHOCERCA_KOSTEI_SEGERS_1993",
          "name": "Trichocerca kostei Segers, 1993",
          "rank": "SPECIES",
          "commonName": "Trichocerca Kostei Segers, 1993",
          "lineage": "Trichocerca",
          "subspeciesCount": 0,
          "description": "Trichocerca kostei Segers, 1993 — a eurotatoria species in the genus Trichocerca.",
          "sourcedFrom": "generated"
        },
        {
          "id": "SP_TRICHOCERCA_LATA",
          "name": "Trichocerca lata",
          "rank": "SPECIES",
          "commonName": "Trichocerca Lata",
          "lineage": "Trichocerca",
          "subspeciesCount": 0,
          "description": "Trichocerca lata — a eurotatoria species in the genus Trichocerca.",
          "sourcedFrom": "generated"
        },
        {
          "id": "SP_TRICHOCERCA_LONGISETA",
          "name": "Trichocerca longiseta",
          "rank": "SPECIES",
          "commonName": "Trichocerca Longiseta",
          "lineage": "Trichocerca",
          "subspeciesCount": 0,
          "description": "Trichocerca longiseta — a eurotatoria species in the genus Trichocerca.",
          "sourcedFrom": "generated"
        },
        {
          "id": "SP_TRICHOCERCA_LONGISTYLA",
          "name": "Trichocerca longistyla",
          "rank": "SPECIES",
          "commonName": "Trichocerca Longistyla",
          "lineage": "Trichocerca",
          "subspeciesCount": 0,
          "description": "Trichocerca longistyla — a eurotatoria species in the genus Trichocerca.",
          "sourcedFrom": "generated"
        },
        {
          "id": "SP_TRICHOCERCA_LOPHOESSA",
          "name": "Trichocerca lophoessa",
          "rank": "SPECIES",
          "commonName": "Trichocerca Lophoessa",
          "lineage": "Trichocerca",
          "subspeciesCount": 0,
          "description": "Trichocerca lophoessa — a eurotatoria species in the genus Trichocerca.",
          "sourcedFrom": "generated"
        },
        {
          "id": "SP_TRICHOCERCA_MACERA",
          "name": "Trichocerca macera",
          "rank": "SPECIES",
          "commonName": "Trichocerca Macera",
          "lineage": "Trichocerca",
          "subspeciesCount": 0,
          "description": "Trichocerca macera — a eurotatoria species in the genus Trichocerca.",
          "sourcedFrom": "generated"
        },
        {
          "id": "SP_TRICHOCERCA_MAIOR",
          "name": "Trichocerca maior",
          "rank": "SPECIES",
          "commonName": "Trichocerca Maior",
          "lineage": "Trichocerca",
          "subspeciesCount": 0,
          "description": "Trichocerca maior — a eurotatoria species in the genus Trichocerca.",
          "sourcedFrom": "generated"
        },
        {
          "id": "SP_TRICHOCERCA_MARINA",
          "name": "Trichocerca marina",
          "rank": "SPECIES",
          "commonName": "Trichocerca Marina",
          "lineage": "Trichocerca",
          "subspeciesCount": 0,
          "description": "Trichocerca marina — a eurotatoria species in the genus Trichocerca.",
          "sourcedFrom": "generated"
        },
        {
          "id": "SP_TRICHOCERCA_MICROSTYLA",
          "name": "Trichocerca microstyla",
          "rank": "SPECIES",
          "commonName": "Trichocerca Microstyla",
          "lineage": "Trichocerca",
          "subspeciesCount": 0,
          "description": "Trichocerca microstyla — a eurotatoria species in the genus Trichocerca.",
          "sourcedFrom": "generated"
        },
        {
          "id": "SP_TRICHOCERCA_MINUTA",
          "name": "Trichocerca minuta",
          "rank": "SPECIES",
          "commonName": "Trichocerca Minuta",
          "lineage": "Trichocerca",
          "subspeciesCount": 0,
          "description": "Trichocerca minuta — a eurotatoria species in the genus Trichocerca.",
          "sourcedFrom": "generated"
        },
        {
          "id": "SP_TRICHOCERCA_MOLLIS_EDMONDSON_1936",
          "name": "Trichocerca mollis Edmondson, 1936",
          "rank": "SPECIES",
          "commonName": "Trichocerca Mollis Edmondson, 1936",
          "lineage": "Trichocerca",
          "subspeciesCount": 0,
          "description": "Trichocerca mollis Edmondson, 1936 — a eurotatoria species in the genus Trichocerca.",
          "sourcedFrom": "generated"
        },
        {
          "id": "SP_TRICHOCERCA_MUCOSA",
          "name": "Trichocerca mucosa",
          "rank": "SPECIES",
          "commonName": "Trichocerca Mucosa",
          "lineage": "Trichocerca",
          "subspeciesCount": 0,
          "description": "Trichocerca mucosa — a eurotatoria species in the genus Trichocerca.",
          "sourcedFrom": "generated"
        },
        {
          "id": "SP_TRICHOCERCA_MUCRIPES_AHLSTROM_1938",
          "name": "Trichocerca mucripes Ahlstrom, 1938",
          "rank": "SPECIES",
          "commonName": "Trichocerca Mucripes Ahlstrom, 1938",
          "lineage": "Trichocerca",
          "subspeciesCount": 0,
          "description": "Trichocerca mucripes Ahlstrom, 1938 — a eurotatoria species in the genus Trichocerca.",
          "sourcedFrom": "generated"
        },
        {
          "id": "SP_TRICHOCERCA_MULTICRINIS",
          "name": "Trichocerca multicrinis",
          "rank": "SPECIES",
          "commonName": "Trichocerca Multicrinis",
          "lineage": "Trichocerca",
          "subspeciesCount": 0,
          "description": "Trichocerca multicrinis — a eurotatoria species in the genus Trichocerca.",
          "sourcedFrom": "generated"
        },
        {
          "id": "SP_TRICHOCERCA_MURCHIEARUM_EDMONDSON_1936",
          "name": "Trichocerca murchiearum Edmondson, 1936",
          "rank": "SPECIES",
          "commonName": "Trichocerca Murchiearum Edmondson, 1936",
          "lineage": "Trichocerca",
          "subspeciesCount": 0,
          "description": "Trichocerca murchiearum Edmondson, 1936 — a eurotatoria species in the genus Trichocerca.",
          "sourcedFrom": "generated"
        },
        {
          "id": "SP_TRICHOCERCA_MUS_HAUER_1938",
          "name": "Trichocerca mus Hauer, 1938",
          "rank": "SPECIES",
          "commonName": "Trichocerca Mus Hauer, 1938",
          "lineage": "Trichocerca",
          "subspeciesCount": 0,
          "description": "Trichocerca mus Hauer, 1938 — a eurotatoria species in the genus Trichocerca.",
          "sourcedFrom": "generated"
        },
        {
          "id": "SP_TRICHOCERCA_MUSCULUS",
          "name": "Trichocerca musculus",
          "rank": "SPECIES",
          "commonName": "Trichocerca Musculus",
          "lineage": "Trichocerca",
          "subspeciesCount": 0,
          "description": "Trichocerca musculus — a eurotatoria species in the genus Trichocerca.",
          "sourcedFrom": "generated"
        },
        {
          "id": "SP_TRICHOCERCA_MYERSI",
          "name": "Trichocerca myersi",
          "rank": "SPECIES",
          "commonName": "Trichocerca Myersi",
          "lineage": "Trichocerca",
          "subspeciesCount": 0,
          "description": "Trichocerca myersi — a eurotatoria species in the genus Trichocerca.",
          "sourcedFrom": "generated"
        },
        {
          "id": "SP_TRICHOCERCA_NITIDA_HARRING_1914",
          "name": "Trichocerca nitida Harring, 1914",
          "rank": "SPECIES",
          "commonName": "Trichocerca Nitida Harring, 1914",
          "lineage": "Trichocerca",
          "subspeciesCount": 0,
          "description": "Trichocerca nitida Harring, 1914 — a eurotatoria species in the genus Trichocerca.",
          "sourcedFrom": "generated"
        },
        {
          "id": "SP_TRICHOCERCA_OBTUSIDENS",
          "name": "Trichocerca obtusidens",
          "rank": "SPECIES",
          "commonName": "Trichocerca Obtusidens",
          "lineage": "Trichocerca",
          "subspeciesCount": 0,
          "description": "Trichocerca obtusidens — a eurotatoria species in the genus Trichocerca.",
          "sourcedFrom": "generated"
        },
        {
          "id": "SP_TRICHOCERCA_ORCA",
          "name": "Trichocerca orca",
          "rank": "SPECIES",
          "commonName": "Trichocerca Orca",
          "lineage": "Trichocerca",
          "subspeciesCount": 0,
          "description": "Trichocerca orca — a eurotatoria species in the genus Trichocerca.",
          "sourcedFrom": "generated"
        },
        {
          "id": "SP_TRICHOCERCA_ORNATA_MYERS_1934",
          "name": "Trichocerca ornata Myers, 1934",
          "rank": "SPECIES",
          "commonName": "Trichocerca Ornata Myers, 1934",
          "lineage": "Trichocerca",
          "subspeciesCount": 0,
          "description": "Trichocerca ornata Myers, 1934 — a eurotatoria species in the genus Trichocerca.",
          "sourcedFrom": "generated"
        },
        {
          "id": "SP_TRICHOCERCA_PARVA",
          "name": "Trichocerca parva",
          "rank": "SPECIES",
          "commonName": "Trichocerca Parva",
          "lineage": "Trichocerca",
          "subspeciesCount": 0,
          "description": "Trichocerca parva — a eurotatoria species in the genus Trichocerca.",
          "sourcedFrom": "generated"
        },
        {
          "id": "SP_TRICHOCERCA_PEDICULUS_REMANE_1949",
          "name": "Trichocerca pediculus Remane, 1949",
          "rank": "SPECIES",
          "commonName": "Trichocerca Pediculus Remane, 1949",
          "lineage": "Trichocerca",
          "subspeciesCount": 0,
          "description": "Trichocerca pediculus Remane, 1949 — a eurotatoria species in the genus Trichocerca.",
          "sourcedFrom": "generated"
        },
        {
          "id": "SP_TRICHOCERCA_PLAKA_MYERS_1938",
          "name": "Trichocerca plaka Myers, 1938",
          "rank": "SPECIES",
          "commonName": "Trichocerca Plaka Myers, 1938",
          "lineage": "Trichocerca",
          "subspeciesCount": 0,
          "description": "Trichocerca plaka Myers, 1938 — a eurotatoria species in the genus Trichocerca.",
          "sourcedFrom": "generated"
        },
        {
          "id": "SP_TRICHOCERCA_PLATESSA_MYERS_1934",
          "name": "Trichocerca platessa Myers, 1934",
          "rank": "SPECIES",
          "commonName": "Trichocerca Platessa Myers, 1934",
          "lineage": "Trichocerca",
          "subspeciesCount": 0,
          "description": "Trichocerca platessa Myers, 1934 — a eurotatoria species in the genus Trichocerca.",
          "sourcedFrom": "generated"
        },
        {
          "id": "SP_TRICHOCERCA_PORCELLUS",
          "name": "Trichocerca porcellus",
          "rank": "SPECIES",
          "commonName": "Trichocerca Porcellus",
          "lineage": "Trichocerca",
          "subspeciesCount": 0,
          "description": "Trichocerca porcellus — a eurotatoria species in the genus Trichocerca.",
          "sourcedFrom": "generated"
        },
        {
          "id": "SP_TRICHOCERCA_PUSILLA",
          "name": "Trichocerca pusilla",
          "rank": "SPECIES",
          "commonName": "Trichocerca Pusilla",
          "lineage": "Trichocerca",
          "subspeciesCount": 0,
          "description": "Trichocerca pusilla — a eurotatoria species in the genus Trichocerca.",
          "sourcedFrom": "generated"
        },
        {
          "id": "SP_TRICHOCERCA_PUSTILLA",
          "name": "Trichocerca pustilla",
          "rank": "SPECIES",
          "commonName": "Trichocerca Pustilla",
          "lineage": "Trichocerca",
          "subspeciesCount": 0,
          "description": "Trichocerca pustilla — a eurotatoria species in the genus Trichocerca.",
          "sourcedFrom": "generated"
        },
        {
          "id": "SP_TRICHOCERCA_PYGOCERA",
          "name": "Trichocerca pygocera",
          "rank": "SPECIES",
          "commonName": "Trichocerca Pygocera",
          "lineage": "Trichocerca",
          "subspeciesCount": 0,
          "description": "Trichocerca pygocera — a eurotatoria species in the genus Trichocerca.",
          "sourcedFrom": "generated"
        },
        {
          "id": "SP_TRICHOCERCA_RATTUS",
          "name": "Trichocerca rattus",
          "rank": "SPECIES",
          "commonName": "Trichocerca Rattus",
          "lineage": "Trichocerca",
          "subspeciesCount": 0,
          "description": "Trichocerca rattus — a eurotatoria species in the genus Trichocerca.",
          "sourcedFrom": "generated"
        },
        {
          "id": "SP_TRICHOCERCA_RECTANGULARIS_EVENS_1947",
          "name": "Trichocerca rectangularis Evens, 1947",
          "rank": "SPECIES",
          "commonName": "Trichocerca Rectangularis Evens, 1947",
          "lineage": "Trichocerca",
          "subspeciesCount": 0,
          "description": "Trichocerca rectangularis Evens, 1947 — a eurotatoria species in the genus Trichocerca.",
          "sourcedFrom": "generated"
        },
        {
          "id": "SP_TRICHOCERCA_RIPLI_BERZIN_1973",
          "name": "Trichocerca ripli Berzinš, 1973",
          "rank": "SPECIES",
          "commonName": "Trichocerca Ripli Berzinš, 1973",
          "lineage": "Trichocerca",
          "subspeciesCount": 0,
          "description": "Trichocerca ripli Berzinš, 1973 — a eurotatoria species in the genus Trichocerca.",
          "sourcedFrom": "generated"
        },
        {
          "id": "SP_TRICHOCERCA_ROSEA",
          "name": "Trichocerca rosea",
          "rank": "SPECIES",
          "commonName": "Trichocerca Rosea",
          "lineage": "Trichocerca",
          "subspeciesCount": 0,
          "description": "Trichocerca rosea — a eurotatoria species in the genus Trichocerca.",
          "sourcedFrom": "generated"
        },
        {
          "id": "SP_TRICHOCERCA_ROTUNDATA_MYERS_1937",
          "name": "Trichocerca rotundata Myers, 1937",
          "rank": "SPECIES",
          "commonName": "Trichocerca Rotundata Myers, 1937",
          "lineage": "Trichocerca",
          "subspeciesCount": 0,
          "description": "Trichocerca rotundata Myers, 1937 — a eurotatoria species in the genus Trichocerca.",
          "sourcedFrom": "generated"
        },
        {
          "id": "SP_TRICHOCERCA_ROUSSELETI",
          "name": "Trichocerca rousseleti",
          "rank": "SPECIES",
          "commonName": "Trichocerca Rousseleti",
          "lineage": "Trichocerca",
          "subspeciesCount": 0,
          "description": "Trichocerca rousseleti — a eurotatoria species in the genus Trichocerca.",
          "sourcedFrom": "generated"
        },
        {
          "id": "SP_TRICHOCERCA_RUTTNERI_DONNER_1953",
          "name": "Trichocerca ruttneri Donner, 1953",
          "rank": "SPECIES",
          "commonName": "Trichocerca Ruttneri Donner, 1953",
          "lineage": "Trichocerca",
          "subspeciesCount": 0,
          "description": "Trichocerca ruttneri Donner, 1953 — a eurotatoria species in the genus Trichocerca.",
          "sourcedFrom": "generated"
        },
        {
          "id": "SP_TRICHOCERCA_SCIPIO",
          "name": "Trichocerca scipio",
          "rank": "SPECIES",
          "commonName": "Trichocerca Scipio",
          "lineage": "Trichocerca",
          "subspeciesCount": 0,
          "description": "Trichocerca scipio — a eurotatoria species in the genus Trichocerca.",
          "sourcedFrom": "generated"
        },
        {
          "id": "SP_TRICHOCERCA_SEJUNCTIPES",
          "name": "Trichocerca sejunctipes",
          "rank": "SPECIES",
          "commonName": "Trichocerca Sejunctipes",
          "lineage": "Trichocerca",
          "subspeciesCount": 0,
          "description": "Trichocerca sejunctipes — a eurotatoria species in the genus Trichocerca.",
          "sourcedFrom": "generated"
        },
        {
          "id": "SP_TRICHOCERCA_SIAMENSIS_SEGERS_PHOLPUNTHIN_1997",
          "name": "Trichocerca siamensis Segers & Pholpunthin, 1997",
          "rank": "SPECIES",
          "commonName": "Trichocerca Siamensis Segers & Pholpunthin, 1997",
          "lineage": "Trichocerca",
          "subspeciesCount": 0,
          "description": "Trichocerca siamensis Segers & Pholpunthin, 1997 — a eurotatoria species in the genus Trichocerca.",
          "sourcedFrom": "generated"
        },
        {
          "id": "SP_TRICHOCERCA_SIMILIS",
          "name": "Trichocerca similis",
          "rank": "SPECIES",
          "commonName": "Trichocerca Similis",
          "lineage": "Trichocerca",
          "subspeciesCount": 0,
          "description": "Trichocerca similis — a eurotatoria species in the genus Trichocerca.",
          "sourcedFrom": "generated"
        },
        {
          "id": "SP_TRICHOCERCA_SIMONEAE_DE_SMET_1990",
          "name": "Trichocerca simoneae De Smet, 1990",
          "rank": "SPECIES",
          "commonName": "Trichocerca Simoneae De Smet, 1990",
          "lineage": "Trichocerca",
          "subspeciesCount": 0,
          "description": "Trichocerca simoneae De Smet, 1990 — a eurotatoria species in the genus Trichocerca.",
          "sourcedFrom": "generated"
        },
        {
          "id": "SP_TRICHOCERCA_STYLATA",
          "name": "Trichocerca stylata",
          "rank": "SPECIES",
          "commonName": "Trichocerca Stylata",
          "lineage": "Trichocerca",
          "subspeciesCount": 0,
          "description": "Trichocerca stylata — a eurotatoria species in the genus Trichocerca.",
          "sourcedFrom": "generated"
        },
        {
          "id": "SP_TRICHOCERCA_SULCATA",
          "name": "Trichocerca sulcata",
          "rank": "SPECIES",
          "commonName": "Trichocerca Sulcata",
          "lineage": "Trichocerca",
          "subspeciesCount": 0,
          "description": "Trichocerca sulcata — a eurotatoria species in the genus Trichocerca.",
          "sourcedFrom": "generated"
        },
        {
          "id": "SP_TRICHOCERCA_TAUROCEPHALA",
          "name": "Trichocerca taurocephala",
          "rank": "SPECIES",
          "commonName": "Trichocerca Taurocephala",
          "lineage": "Trichocerca",
          "subspeciesCount": 0,
          "description": "Trichocerca taurocephala — a eurotatoria species in the genus Trichocerca.",
          "sourcedFrom": "generated"
        },
        {
          "id": "SP_TRICHOCERCA_TENUIDENS",
          "name": "Trichocerca tenuidens",
          "rank": "SPECIES",
          "commonName": "Trichocerca Tenuidens",
          "lineage": "Trichocerca",
          "subspeciesCount": 0,
          "description": "Trichocerca tenuidens — a eurotatoria species in the genus Trichocerca.",
          "sourcedFrom": "generated"
        },
        {
          "id": "SP_TRICHOCERCA_TENUIOR",
          "name": "Trichocerca tenuior",
          "rank": "SPECIES",
          "commonName": "Trichocerca Tenuior",
          "lineage": "Trichocerca",
          "subspeciesCount": 0,
          "description": "Trichocerca tenuior — a eurotatoria species in the genus Trichocerca.",
          "sourcedFrom": "generated"
        },
        {
          "id": "SP_TRICHOCERCA_TIGRIS",
          "name": "Trichocerca tigris",
          "rank": "SPECIES",
          "commonName": "Trichocerca Tigris",
          "lineage": "Trichocerca",
          "subspeciesCount": 0,
          "description": "Trichocerca tigris — a eurotatoria species in the genus Trichocerca.",
          "sourcedFrom": "generated"
        },
        {
          "id": "SP_TRICHOCERCA_UNCINATA",
          "name": "Trichocerca uncinata",
          "rank": "SPECIES",
          "commonName": "Trichocerca Uncinata",
          "lineage": "Trichocerca",
          "subspeciesCount": 0,
          "description": "Trichocerca uncinata — a eurotatoria species in the genus Trichocerca.",
          "sourcedFrom": "generated"
        },
        {
          "id": "SP_TRICHOCERCA_UNIDENS",
          "name": "Trichocerca unidens",
          "rank": "SPECIES",
          "commonName": "Trichocerca Unidens",
          "lineage": "Trichocerca",
          "subspeciesCount": 0,
          "description": "Trichocerca unidens — a eurotatoria species in the genus Trichocerca.",
          "sourcedFrom": "generated"
        },
        {
          "id": "SP_TRICHOCERCA_VALGA",
          "name": "Trichocerca valga",
          "rank": "SPECIES",
          "commonName": "Trichocerca Valga",
          "lineage": "Trichocerca",
          "subspeciesCount": 0,
          "description": "Trichocerca valga — a eurotatoria species in the genus Trichocerca.",
          "sourcedFrom": "generated"
        },
        {
          "id": "SP_TRICHOCERCA_VARGAI_WULFERT_1961",
          "name": "Trichocerca vargai Wulfert, 1961",
          "rank": "SPECIES",
          "commonName": "Trichocerca Vargai Wulfert, 1961",
          "lineage": "Trichocerca",
          "subspeciesCount": 0,
          "description": "Trichocerca vargai Wulfert, 1961 — a eurotatoria species in the genus Trichocerca.",
          "sourcedFrom": "generated"
        },
        {
          "id": "SP_TRICHOCERCA_VASSILIJEVAE_KUTIKOVA_1985",
          "name": "Trichocerca vassilijevae Kutikova, 1985",
          "rank": "SPECIES",
          "commonName": "Trichocerca Vassilijevae Kutikova, 1985",
          "lineage": "Trichocerca",
          "subspeciesCount": 0,
          "description": "Trichocerca vassilijevae Kutikova, 1985 — a eurotatoria species in the genus Trichocerca.",
          "sourcedFrom": "generated"
        },
        {
          "id": "SP_TRICHOCERCA_VERNALIS",
          "name": "Trichocerca vernalis",
          "rank": "SPECIES",
          "commonName": "Trichocerca Vernalis",
          "lineage": "Trichocerca",
          "subspeciesCount": 0,
          "description": "Trichocerca vernalis — a eurotatoria species in the genus Trichocerca.",
          "sourcedFrom": "generated"
        },
        {
          "id": "SP_TRICHOCERCA_VOLUTA",
          "name": "Trichocerca voluta",
          "rank": "SPECIES",
          "commonName": "Trichocerca Voluta",
          "lineage": "Trichocerca",
          "subspeciesCount": 0,
          "description": "Trichocerca voluta — a eurotatoria species in the genus Trichocerca.",
          "sourcedFrom": "generated"
        },
        {
          "id": "SP_TRICHOCERCA_WANARRA_SEGERS_SHIEL_2003",
          "name": "Trichocerca wanarra Segers & Shiel, 2003",
          "rank": "SPECIES",
          "commonName": "Trichocerca Wanarra Segers & Shiel, 2003",
          "lineage": "Trichocerca",
          "subspeciesCount": 0,
          "description": "Trichocerca wanarra Segers & Shiel, 2003 — a eurotatoria species in the genus Trichocerca.",
          "sourcedFrom": "generated"
        },
        {
          "id": "SP_TRICHOCERCA_WEBERI",
          "name": "Trichocerca weberi",
          "rank": "SPECIES",
          "commonName": "Trichocerca Weberi",
          "lineage": "Trichocerca",
          "subspeciesCount": 0,
          "description": "Trichocerca weberi — a eurotatoria species in the genus Trichocerca.",
          "sourcedFrom": "generated"
        }
      ]
    }
  ]
}
