{
  "id": "FAM_GARDINERIIDAE",
  "name": "Gardineriidae",
  "rank": "FAMILY",
  "commonName": "Gardineriidae",
  "children": [
    {
      "id": "GENUS_STOLARSKICYATHUS",
      "name": "Stolarskicyathus",
      "rank": "GENUS",
      "description": "Stolarskicyathus — a genus of anthozoas.",
      "lineage": "Stolarskicyathus",
      "children": [
        {
          "id": "SP_STOLARSKICYATHUS_POCILLIFORMIS_CAIRNS_2004",
          "name": "Stolarskicyathus pocilliformis Cairns, 2004",
          "rank": "SPECIES",
          "commonName": "Stolarskicyathus Pocilliformis Cairns, 2004",
          "lineage": "Stolarskicyathus",
          "subspeciesCount": 0,
          "description": "Stolarskicyathus pocilliformis Cairns, 2004 — a anthozoa species in the genus Stolarskicyathus.",
          "sourcedFrom": "generated"
        }
      ]
    },
    {
      "id": "GENUS_GARDINERIA",
      "name": "Gardineria",
      "rank": "GENUS",
      "description": "Gardineria — a genus of anthozoas.",
      "lineage": "Gardineria",
      "children": [
        {
          "id": "SP_GARDINERIA_ALLOITEAUI_KITAHARA_CAIRNS_2021",
          "name": "Gardineria alloiteaui Kitahara & Cairns, 2021",
          "rank": "SPECIES",
          "commonName": "Gardineria Alloiteaui Kitahara & Cairns, 2021",
          "lineage": "Gardineria",
          "subspeciesCount": 0,
          "description": "Gardineria alloiteaui Kitahara & Cairns, 2021 — a anthozoa species in the genus Gardineria.",
          "sourcedFrom": "generated"
        },
        {
          "id": "SP_GARDINERIA_HAWAIIENSIS_VAUGHAN_1907",
          "name": "Gardineria hawaiiensis Vaughan, 1907",
          "rank": "SPECIES",
          "commonName": "Gardineria Hawaiiensis Vaughan, 1907",
          "lineage": "Gardineria",
          "subspeciesCount": 0,
          "description": "Gardineria hawaiiensis Vaughan, 1907 — a anthozoa species in the genus Gardineria.",
          "sourcedFrom": "generated"
        },
        {
          "id": "SP_GARDINERIA_MINOR_WELLS_1973",
          "name": "Gardineria minor Wells, 1973",
          "rank": "SPECIES",
          "commonName": "Gardineria Minor Wells, 1973",
          "lineage": "Gardineria",
          "subspeciesCount": 0,
          "description": "Gardineria minor Wells, 1973 — a anthozoa species in the genus Gardineria.",
          "sourcedFrom": "generated"
        },
        {
          "id": "SP_GARDINERIA_PARADOXA",
          "name": "Gardineria paradoxa",
          "rank": "SPECIES",
          "commonName": "Gardineria Paradoxa",
          "lineage": "Gardineria",
          "subspeciesCount": 0,
          "description": "Gardineria paradoxa — a anthozoa species in the genus Gardineria.",
          "sourcedFrom": "generated"
        },
        {
          "id": "SP_GARDINERIA_PHILIPPINENSIS_CAIRNS_1989",
          "name": "Gardineria philippinensis Cairns, 1989",
          "rank": "SPECIES",
          "commonName": "Gardineria Philippinensis Cairns, 1989",
          "lineage": "Gardineria",
          "subspeciesCount": 0,
          "description": "Gardineria philippinensis Cairns, 1989 — a anthozoa species in the genus Gardineria.",
          "sourcedFrom": "generated"
        },
        {
          "id": "SP_GARDINERIA_SIMOJOVELENSIS_FROST_LANGENHEIM_1974",
          "name": "Gardineria simojovelensis Frost & Langenheim, 1974",
          "rank": "SPECIES",
          "commonName": "Gardineria Simojovelensis Frost & Langenheim, 1974",
          "lineage": "Gardineria",
          "subspeciesCount": 0,
          "description": "Gardineria simojovelensis Frost & Langenheim, 1974 — a anthozoa species in the genus Gardineria.",
          "sourcedFrom": "generated"
        },
        {
          "id": "SP_GARDINERIA_SIMPLEX",
          "name": "Gardineria simplex",
          "rank": "SPECIES",
          "commonName": "Gardineria Simplex",
          "lineage": "Gardineria",
          "subspeciesCount": 0,
          "description": "Gardineria simplex — a anthozoa species in the genus Gardineria.",
          "sourcedFrom": "generated"
        }
      ]
    },
    {
      "id": "GENUS_ADKINSELLA",
      "name": "Adkinsella",
      "rank": "GENUS",
      "description": "Adkinsella — a genus of anthozoas.",
      "lineage": "Adkinsella",
      "children": [
        {
          "id": "SP_ADKINSELLA_EDWARDSENIS_WELLS_1933",
          "name": "Adkinsella edwardsenis Wells, 1933",
          "rank": "SPECIES",
          "commonName": "Adkinsella Edwardsenis Wells, 1933",
          "lineage": "Adkinsella",
          "subspeciesCount": 0,
          "description": "Adkinsella edwardsenis Wells, 1933 — a anthozoa species in the genus Adkinsella.",
          "sourcedFrom": "generated"
        },
        {
          "id": "SP_ADKINSELLA_EDWARDSENSIS_WELLS_1933",
          "name": "Adkinsella edwardsensis Wells, 1933",
          "rank": "SPECIES",
          "commonName": "Adkinsella Edwardsensis Wells, 1933",
          "lineage": "Adkinsella",
          "subspeciesCount": 0,
          "description": "Adkinsella edwardsensis Wells, 1933 — a anthozoa species in the genus Adkinsella.",
          "sourcedFrom": "generated"
        },
        {
          "id": "SP_HEXASMILIOPSIS_SALDANAI_L_SER_2008",
          "name": "Hexasmiliopsis saldanai Löser, 2008",
          "rank": "SPECIES",
          "commonName": "Adkinsella Saldanai LöSer, 2008",
          "lineage": "Adkinsella",
          "subspeciesCount": 0,
          "description": "Hexasmiliopsis saldanai Löser, 2008 — a anthozoa species in the genus Adkinsella.",
          "sourcedFrom": "generated"
        }
      ]
    }
  ]
}
