{
  "id": "FAM_SEMISULCOSPIRIDAE",
  "name": "Semisulcospiridae",
  "rank": "FAMILY",
  "commonName": "Semisulcospiridae",
  "children": [
    {
      "id": "GENUS_JUGA",
      "name": "Juga",
      "rank": "GENUS",
      "description": "Juga — a genus of gastropodas.",
      "lineage": "Juga",
      "children": [
        {
          "id": "SP_JUGA_ACUTIFILOSA",
          "name": "Juga acutifilosa",
          "rank": "SPECIES",
          "commonName": "Juga Acutifilosa",
          "lineage": "Juga",
          "subspeciesCount": 0,
          "description": "Juga acutifilosa — a gastropoda species in the genus Juga.",
          "sourcedFrom": "generated"
        },
        {
          "id": "SP_JUGA_AMGUNICA_MOSKVICHEVA_1986",
          "name": "Juga amgunica Moskvicheva, 1986",
          "rank": "SPECIES",
          "commonName": "Juga Amgunica Moskvicheva, 1986",
          "lineage": "Juga",
          "subspeciesCount": 0,
          "description": "Juga amgunica Moskvicheva, 1986 — a gastropoda species in the genus Juga.",
          "sourcedFrom": "generated"
        },
        {
          "id": "SP_JUGA_ARNOLDIANA",
          "name": "Juga arnoldiana",
          "rank": "SPECIES",
          "commonName": "Juga Arnoldiana",
          "lineage": "Juga",
          "subspeciesCount": 0,
          "description": "Juga arnoldiana — a gastropoda species in the genus Juga.",
          "sourcedFrom": "generated"
        },
        {
          "id": "SP_JUGA_BUETTNERI",
          "name": "Juga buettneri",
          "rank": "SPECIES",
          "commonName": "Juga Buettneri",
          "lineage": "Juga",
          "subspeciesCount": 0,
          "description": "Juga buettneri — a gastropoda species in the genus Juga.",
          "sourcedFrom": "generated"
        },
        {
          "id": "SP_JUGA_BULBOSA",
          "name": "Juga bulbosa",
          "rank": "SPECIES",
          "commonName": "Juga Bulbosa",
          "lineage": "Juga",
          "subspeciesCount": 0,
          "description": "Juga bulbosa — a gastropoda species in the genus Juga.",
          "sourcedFrom": "generated"
        },
        {
          "id": "SP_JUGA_CHANKENSIS_MOSKVICHEVA_1986",
          "name": "Juga chankensis Moskvicheva, 1986",
          "rank": "SPECIES",
          "commonName": "Juga Chankensis Moskvicheva, 1986",
          "lineage": "Juga",
          "subspeciesCount": 0,
          "description": "Juga chankensis Moskvicheva, 1986 — a gastropoda species in the genus Juga.",
          "sourcedFrom": "generated"
        },
        {
          "id": "SP_JUGA_CHRYSOPYLICA_D_W_TAYLOR_1966",
          "name": "Juga chrysopylica D.W.Taylor, 1966",
          "rank": "SPECIES",
          "commonName": "Juga Chrysopylica D.W.Taylor, 1966",
          "lineage": "Juga",
          "subspeciesCount": 0,
          "description": "Juga chrysopylica D.W.Taylor, 1966 — a gastropoda species in the genus Juga.",
          "sourcedFrom": "generated"
        },
        {
          "id": "SP_JUGA_CZERSKII_MOSKVICHEVA_1986",
          "name": "Juga czerskii Moskvicheva, 1986",
          "rank": "SPECIES",
          "commonName": "Juga Czerskii Moskvicheva, 1986",
          "lineage": "Juga",
          "subspeciesCount": 0,
          "description": "Juga czerskii Moskvicheva, 1986 — a gastropoda species in the genus Juga.",
          "sourcedFrom": "generated"
        },
        {
          "id": "SP_JUGA_KETTLEMANENSIS",
          "name": "Juga kettlemanensis",
          "rank": "SPECIES",
          "commonName": "Juga Kettlemanensis",
          "lineage": "Juga",
          "subspeciesCount": 0,
          "description": "Juga kettlemanensis — a gastropoda species in the genus Juga.",
          "sourcedFrom": "generated"
        },
        {
          "id": "SP_JUGA_NEWBERRYI",
          "name": "Juga newberryi",
          "rank": "SPECIES",
          "commonName": "Juga Newberryi",
          "lineage": "Juga",
          "subspeciesCount": 0,
          "description": "Juga newberryi — a gastropoda species in the genus Juga.",
          "sourcedFrom": "generated"
        },
        {
          "id": "SP_JUGA_NIGRINA",
          "name": "Juga nigrina",
          "rank": "SPECIES",
          "commonName": "Juga Nigrina",
          "lineage": "Juga",
          "subspeciesCount": 0,
          "description": "Juga nigrina — a gastropoda species in the genus Juga.",
          "sourcedFrom": "generated"
        },
        {
          "id": "SP_JUGA_NODOSA",
          "name": "Juga nodosa",
          "rank": "SPECIES",
          "commonName": "Juga Nodosa",
          "lineage": "Juga",
          "subspeciesCount": 0,
          "description": "Juga nodosa — a gastropoda species in the genus Juga.",
          "sourcedFrom": "generated"
        },
        {
          "id": "SP_JUGA_OCCATA",
          "name": "Juga occata",
          "rank": "SPECIES",
          "commonName": "Juga Occata",
          "lineage": "Juga",
          "subspeciesCount": 0,
          "description": "Juga occata — a gastropoda species in the genus Juga.",
          "sourcedFrom": "generated"
        },
        {
          "id": "SP_JUGA_ORCHONICA_POPOVA_1981",
          "name": "Juga orchonica Popova, 1981",
          "rank": "SPECIES",
          "commonName": "Juga Orchonica Popova, 1981",
          "lineage": "Juga",
          "subspeciesCount": 0,
          "description": "Juga orchonica Popova, 1981 — a gastropoda species in the genus Juga.",
          "sourcedFrom": "generated"
        },
        {
          "id": "SP_JUGA_PLICIFERA",
          "name": "Juga plicifera",
          "rank": "SPECIES",
          "commonName": "Juga Plicifera",
          "lineage": "Juga",
          "subspeciesCount": 0,
          "description": "Juga plicifera — a gastropoda species in the genus Juga.",
          "sourcedFrom": "generated"
        },
        {
          "id": "SP_JUGA_STAROBOGATOVI_POPOVA_1981",
          "name": "Juga starobogatovi Popova, 1981",
          "rank": "SPECIES",
          "commonName": "Juga Starobogatovi Popova, 1981",
          "lineage": "Juga",
          "subspeciesCount": 0,
          "description": "Juga starobogatovi Popova, 1981 — a gastropoda species in the genus Juga.",
          "sourcedFrom": "generated"
        },
        {
          "id": "SP_JUGA_TUGURENSIS_MOSKVICHEVA_1986",
          "name": "Juga tugurensis Moskvicheva, 1986",
          "rank": "SPECIES",
          "commonName": "Juga Tugurensis Moskvicheva, 1986",
          "lineage": "Juga",
          "subspeciesCount": 0,
          "description": "Juga tugurensis Moskvicheva, 1986 — a gastropoda species in the genus Juga.",
          "sourcedFrom": "generated"
        }
      ]
    },
    {
      "id": "GENUS_SEMISULCOSPIRA",
      "name": "Semisulcospira",
      "rank": "GENUS",
      "description": "Semisulcospira — a genus of gastropodas.",
      "lineage": "Semisulcospira",
      "children": [
        {
          "id": "SP_SEMISULCOSPIRA_ARENICOLA_N_WATANABE_NISHINO_1995",
          "name": "Semisulcospira arenicola N.Watanabe & Nishino, 1995",
          "rank": "SPECIES",
          "commonName": "Semisulcospira Arenicola N.Watanabe & Nishino, 1995",
          "lineage": "Semisulcospira",
          "subspeciesCount": 0,
          "description": "Semisulcospira arenicola N.Watanabe & Nishino, 1995 — a gastropoda species in the genus Semisulcospira.",
          "sourcedFrom": "generated"
        },
        {
          "id": "SP_SEMISULCOSPIRA_CALCULUS",
          "name": "Semisulcospira calculus",
          "rank": "SPECIES",
          "commonName": "Semisulcospira Calculus",
          "lineage": "Semisulcospira",
          "subspeciesCount": 0,
          "description": "Semisulcospira calculus — a gastropoda species in the genus Semisulcospira.",
          "sourcedFrom": "generated"
        },
        {
          "id": "SP_SEMISULCOSPIRA_CANCELLATA_BENSON_1833",
          "name": "Semisulcospira cancellata Benson, 1833",
          "rank": "SPECIES",
          "commonName": "Semisulcospira Cancellata Benson, 1833",
          "lineage": "Semisulcospira",
          "subspeciesCount": 0,
          "description": "Semisulcospira cancellata Benson, 1833 — a gastropoda species in the genus Semisulcospira.",
          "sourcedFrom": "generated"
        },
        {
          "id": "SP_SEMISULCOSPIRA_CINNAMOMEA",
          "name": "Semisulcospira cinnamomea",
          "rank": "SPECIES",
          "commonName": "Semisulcospira Cinnamomea",
          "lineage": "Semisulcospira",
          "subspeciesCount": 0,
          "description": "Semisulcospira cinnamomea — a gastropoda species in the genus Semisulcospira.",
          "sourcedFrom": "generated"
        },
        {
          "id": "SP_SEMISULCOSPIRA_COREANA",
          "name": "Semisulcospira coreana",
          "rank": "SPECIES",
          "commonName": "Semisulcospira Coreana",
          "lineage": "Semisulcospira",
          "subspeciesCount": 0,
          "description": "Semisulcospira coreana — a gastropoda species in the genus Semisulcospira.",
          "sourcedFrom": "generated"
        },
        {
          "id": "SP_SEMISULCOSPIRA_CRASSICOSTA_Y_Y_LIU_Y_X_WANG_Y_H_DUAN_1994",
          "name": "Semisulcospira crassicosta Y.-Y.Liu, Y.-X.Wang & Y.-H.Duan, 1994",
          "rank": "SPECIES",
          "commonName": "Semisulcospira Crassicosta Y.-Y.Liu, Y.-X.Wang & Y.-H.Duan, 1994",
          "lineage": "Semisulcospira",
          "subspeciesCount": 0,
          "description": "Semisulcospira crassicosta Y.-Y.Liu, Y.-X.Wang & Y.-H.Duan, 1994 — a gastropoda species in the genus Semisulcospira.",
          "sourcedFrom": "generated"
        },
        {
          "id": "SP_SEMISULCOSPIRA_DECIPIENS",
          "name": "Semisulcospira decipiens",
          "rank": "SPECIES",
          "commonName": "Semisulcospira Decipiens",
          "lineage": "Semisulcospira",
          "subspeciesCount": 0,
          "description": "Semisulcospira decipiens — a gastropoda species in the genus Semisulcospira.",
          "sourcedFrom": "generated"
        },
        {
          "id": "SP_SEMISULCOSPIRA_DICKSONI_SMITH_1878",
          "name": "Semisulcospira dicksoni Smith, 1878",
          "rank": "SPECIES",
          "commonName": "Semisulcospira Dicksoni Smith, 1878",
          "lineage": "Semisulcospira",
          "subspeciesCount": 0,
          "description": "Semisulcospira dicksoni Smith, 1878 — a gastropoda species in the genus Semisulcospira.",
          "sourcedFrom": "generated"
        },
        {
          "id": "SP_SEMISULCOSPIRA_DIMINUTA_GREDLER_1887",
          "name": "Semisulcospira diminuta Gredler, 1887",
          "rank": "SPECIES",
          "commonName": "Semisulcospira Diminuta Gredler, 1887",
          "lineage": "Semisulcospira",
          "subspeciesCount": 0,
          "description": "Semisulcospira diminuta Gredler, 1887 — a gastropoda species in the genus Semisulcospira.",
          "sourcedFrom": "generated"
        },
        {
          "id": "SP_SEMISULCOSPIRA_DOLOROSA",
          "name": "Semisulcospira dolorosa",
          "rank": "SPECIES",
          "commonName": "Semisulcospira Dolorosa",
          "lineage": "Semisulcospira",
          "subspeciesCount": 0,
          "description": "Semisulcospira dolorosa — a gastropoda species in the genus Semisulcospira.",
          "sourcedFrom": "generated"
        },
        {
          "id": "SP_SEMISULCOSPIRA_FISCINA",
          "name": "Semisulcospira fiscina",
          "rank": "SPECIES",
          "commonName": "Semisulcospira Fiscina",
          "lineage": "Semisulcospira",
          "subspeciesCount": 0,
          "description": "Semisulcospira fiscina — a gastropoda species in the genus Semisulcospira.",
          "sourcedFrom": "generated"
        },
        {
          "id": "SP_SEMISULCOSPIRA_FORTICOSTA",
          "name": "Semisulcospira forticosta",
          "rank": "SPECIES",
          "commonName": "Semisulcospira Forticosta",
          "lineage": "Semisulcospira",
          "subspeciesCount": 0,
          "description": "Semisulcospira forticosta — a gastropoda species in the genus Semisulcospira.",
          "sourcedFrom": "generated"
        },
        {
          "id": "SP_SEMISULCOSPIRA_FUSCATA_N_WATANABE_NISHINO_1995",
          "name": "Semisulcospira fuscata N.Watanabe & Nishino, 1995",
          "rank": "SPECIES",
          "commonName": "Semisulcospira Fuscata N.Watanabe & Nishino, 1995",
          "lineage": "Semisulcospira",
          "subspeciesCount": 0,
          "description": "Semisulcospira fuscata N.Watanabe & Nishino, 1995 — a gastropoda species in the genus Semisulcospira.",
          "sourcedFrom": "generated"
        },
        {
          "id": "SP_SEMISULCOSPIRA_GAMOENSIS_MATSUOKA_MIURA_2019",
          "name": "Semisulcospira gamoensis Matsuoka & Miura, 2019",
          "rank": "SPECIES",
          "commonName": "Semisulcospira Gamoensis Matsuoka & Miura, 2019",
          "lineage": "Semisulcospira",
          "subspeciesCount": 0,
          "description": "Semisulcospira gamoensis Matsuoka & Miura, 2019 — a gastropoda species in the genus Semisulcospira.",
          "sourcedFrom": "generated"
        },
        {
          "id": "SP_SEMISULCOSPIRA_GOTTSCHEI",
          "name": "Semisulcospira gottschei",
          "rank": "SPECIES",
          "commonName": "Semisulcospira Gottschei",
          "lineage": "Semisulcospira",
          "subspeciesCount": 0,
          "description": "Semisulcospira gottschei — a gastropoda species in the genus Semisulcospira.",
          "sourcedFrom": "generated"
        },
        {
          "id": "SP_SEMISULCOSPIRA_GREDLERI",
          "name": "Semisulcospira gredleri",
          "rank": "SPECIES",
          "commonName": "Semisulcospira Gredleri",
          "lineage": "Semisulcospira",
          "subspeciesCount": 0,
          "description": "Semisulcospira gredleri — a gastropoda species in the genus Semisulcospira.",
          "sourcedFrom": "generated"
        },
        {
          "id": "SP_SEMISULCOSPIRA_HABEI_G_M_DAVIS_1969",
          "name": "Semisulcospira habei G.M.Davis, 1969",
          "rank": "SPECIES",
          "commonName": "Semisulcospira Habei G.M.Davis, 1969",
          "lineage": "Semisulcospira",
          "subspeciesCount": 0,
          "description": "Semisulcospira habei G.M.Davis, 1969 — a gastropoda species in the genus Semisulcospira.",
          "sourcedFrom": "generated"
        },
        {
          "id": "SP_SEMISULCOSPIRA_HONGKONGENSIS_BROT_1874",
          "name": "Semisulcospira hongkongensis Brot, 1874",
          "rank": "SPECIES",
          "commonName": "Semisulcospira Hongkongensis Brot, 1874",
          "lineage": "Semisulcospira",
          "subspeciesCount": 0,
          "description": "Semisulcospira hongkongensis Brot, 1874 — a gastropoda species in the genus Semisulcospira.",
          "sourcedFrom": "generated"
        },
        {
          "id": "SP_SEMISULCOSPIRA_JACQUETI",
          "name": "Semisulcospira jacqueti",
          "rank": "SPECIES",
          "commonName": "Semisulcospira Jacqueti",
          "lineage": "Semisulcospira",
          "subspeciesCount": 0,
          "description": "Semisulcospira jacqueti — a gastropoda species in the genus Semisulcospira.",
          "sourcedFrom": "generated"
        },
        {
          "id": "SP_SEMISULCOSPIRA_KOKUBUENSIS_MATSUOKA_MIURA_2018",
          "name": "Semisulcospira kokubuensis Matsuoka & Miura, 2018",
          "rank": "SPECIES",
          "commonName": "Semisulcospira Kokubuensis Matsuoka & Miura, 2018",
          "lineage": "Semisulcospira",
          "subspeciesCount": 0,
          "description": "Semisulcospira kokubuensis Matsuoka & Miura, 2018 — a gastropoda species in the genus Semisulcospira.",
          "sourcedFrom": "generated"
        },
        {
          "id": "SP_SEMISULCOSPIRA_KURODAI_KAJIYAMA_HABE_1961",
          "name": "Semisulcospira kurodai Kajiyama & Habe, 1961",
          "rank": "SPECIES",
          "commonName": "Semisulcospira Kurodai Kajiyama & Habe, 1961",
          "lineage": "Semisulcospira",
          "subspeciesCount": 0,
          "description": "Semisulcospira kurodai Kajiyama & Habe, 1961 — a gastropoda species in the genus Semisulcospira.",
          "sourcedFrom": "generated"
        },
        {
          "id": "SP_SEMISULCOSPIRA_LIBERTINA",
          "name": "Semisulcospira libertina",
          "rank": "SPECIES",
          "commonName": "Semisulcospira Libertina",
          "lineage": "Semisulcospira",
          "subspeciesCount": 0,
          "description": "Semisulcospira libertina — a gastropoda species in the genus Semisulcospira.",
          "sourcedFrom": "generated"
        },
        {
          "id": "SP_SEMISULCOSPIRA_MARICA_Y_Y_LIU_Y_X_WANG_W_Z_ZHANG_1994",
          "name": "Semisulcospira marica Y.-Y.Liu, Y.-X.Wang & W.-Z.Zhang, 1994",
          "rank": "SPECIES",
          "commonName": "Semisulcospira Marica Y.-Y.Liu, Y.-X.Wang & W.-Z.Zhang, 1994",
          "lineage": "Semisulcospira",
          "subspeciesCount": 0,
          "description": "Semisulcospira marica Y.-Y.Liu, Y.-X.Wang & W.-Z.Zhang, 1994 — a gastropoda species in the genus Semisulcospira.",
          "sourcedFrom": "generated"
        },
        {
          "id": "SP_SEMISULCOSPIRA_MORII_N_C_WATANABE_1984",
          "name": "Semisulcospira morii N.C.Watanabe, 1984",
          "rank": "SPECIES",
          "commonName": "Semisulcospira Morii N.C.Watanabe, 1984",
          "lineage": "Semisulcospira",
          "subspeciesCount": 0,
          "description": "Semisulcospira morii N.C.Watanabe, 1984 — a gastropoda species in the genus Semisulcospira.",
          "sourcedFrom": "generated"
        },
        {
          "id": "SP_SEMISULCOSPIRA_MULTICINCTA",
          "name": "Semisulcospira multicincta",
          "rank": "SPECIES",
          "commonName": "Semisulcospira Multicincta",
          "lineage": "Semisulcospira",
          "subspeciesCount": 0,
          "description": "Semisulcospira multicincta — a gastropoda species in the genus Semisulcospira.",
          "sourcedFrom": "generated"
        },
        {
          "id": "SP_SEMISULCOSPIRA_MULTIGRANOSA",
          "name": "Semisulcospira multigranosa",
          "rank": "SPECIES",
          "commonName": "Semisulcospira Multigranosa",
          "lineage": "Semisulcospira",
          "subspeciesCount": 0,
          "description": "Semisulcospira multigranosa — a gastropoda species in the genus Semisulcospira.",
          "sourcedFrom": "generated"
        },
        {
          "id": "SP_SEMISULCOSPIRA_NAGIENSIS",
          "name": "Semisulcospira nagiensis",
          "rank": "SPECIES",
          "commonName": "Semisulcospira Nagiensis",
          "lineage": "Semisulcospira",
          "subspeciesCount": 0,
          "description": "Semisulcospira nagiensis — a gastropoda species in the genus Semisulcospira.",
          "sourcedFrom": "generated"
        },
        {
          "id": "SP_SEMISULCOSPIRA_NAKAMURAI_MATSUOKA_MIURA_2018",
          "name": "Semisulcospira nakamurai Matsuoka & Miura, 2018",
          "rank": "SPECIES",
          "commonName": "Semisulcospira Nakamurai Matsuoka & Miura, 2018",
          "lineage": "Semisulcospira",
          "subspeciesCount": 0,
          "description": "Semisulcospira nakamurai Matsuoka & Miura, 2018 — a gastropoda species in the genus Semisulcospira.",
          "sourcedFrom": "generated"
        },
        {
          "id": "SP_SEMISULCOSPIRA_NAKASEKOAE",
          "name": "Semisulcospira nakasekoae",
          "rank": "SPECIES",
          "commonName": "Semisulcospira Nakasekoae",
          "lineage": "Semisulcospira",
          "subspeciesCount": 0,
          "description": "Semisulcospira nakasekoae — a gastropoda species in the genus Semisulcospira.",
          "sourcedFrom": "generated"
        },
        {
          "id": "SP_SEMISULCOSPIRA_NAPOENSIS",
          "name": "Semisulcospira napoensis",
          "rank": "SPECIES",
          "commonName": "Semisulcospira Napoensis",
          "lineage": "Semisulcospira",
          "subspeciesCount": 0,
          "description": "Semisulcospira napoensis — a gastropoda species in the genus Semisulcospira.",
          "sourcedFrom": "generated"
        },
        {
          "id": "SP_SEMISULCOSPIRA_NIPONICA",
          "name": "Semisulcospira niponica",
          "rank": "SPECIES",
          "commonName": "Semisulcospira Niponica",
          "lineage": "Semisulcospira",
          "subspeciesCount": 0,
          "description": "Semisulcospira niponica — a gastropoda species in the genus Semisulcospira.",
          "sourcedFrom": "generated"
        },
        {
          "id": "SP_SEMISULCOSPIRA_NODIPERDA",
          "name": "Semisulcospira nodiperda",
          "rank": "SPECIES",
          "commonName": "Semisulcospira Nodiperda",
          "lineage": "Semisulcospira",
          "subspeciesCount": 0,
          "description": "Semisulcospira nodiperda — a gastropoda species in the genus Semisulcospira.",
          "sourcedFrom": "generated"
        },
        {
          "id": "SP_SEMISULCOSPIRA_NOJIRINA_MATSUOKA_MIURA_2019",
          "name": "Semisulcospira nojirina Matsuoka & Miura, 2019",
          "rank": "SPECIES",
          "commonName": "Semisulcospira Nojirina Matsuoka & Miura, 2019",
          "lineage": "Semisulcospira",
          "subspeciesCount": 0,
          "description": "Semisulcospira nojirina Matsuoka & Miura, 2019 — a gastropoda species in the genus Semisulcospira.",
          "sourcedFrom": "generated"
        },
        {
          "id": "SP_SEMISULCOSPIRA_PACIFICANS_HEUDE_1888",
          "name": "Semisulcospira pacificans Heude, 1888",
          "rank": "SPECIES",
          "commonName": "Semisulcospira Pacificans Heude, 1888",
          "lineage": "Semisulcospira",
          "subspeciesCount": 0,
          "description": "Semisulcospira pacificans Heude, 1888 — a gastropoda species in the genus Semisulcospira.",
          "sourcedFrom": "generated"
        },
        {
          "id": "SP_SEMISULCOSPIRA_PRAEMULTIGRANOSA_MATSUOKA_1985",
          "name": "Semisulcospira praemultigranosa Matsuoka, 1985",
          "rank": "SPECIES",
          "commonName": "Semisulcospira Praemultigranosa Matsuoka, 1985",
          "lineage": "Semisulcospira",
          "subspeciesCount": 0,
          "description": "Semisulcospira praemultigranosa Matsuoka, 1985 — a gastropoda species in the genus Semisulcospira.",
          "sourcedFrom": "generated"
        },
        {
          "id": "SP_SEMISULCOSPIRA_PSEUDOMULTIGRANOSA_MATSUOKA_MIURA_2018",
          "name": "Semisulcospira pseudomultigranosa Matsuoka & Miura, 2018",
          "rank": "SPECIES",
          "commonName": "Semisulcospira Pseudomultigranosa Matsuoka & Miura, 2018",
          "lineage": "Semisulcospira",
          "subspeciesCount": 0,
          "description": "Semisulcospira pseudomultigranosa Matsuoka & Miura, 2018 — a gastropoda species in the genus Semisulcospira.",
          "sourcedFrom": "generated"
        },
        {
          "id": "SP_SEMISULCOSPIRA_PUSILLA_MATSUOKA_MIURA_2018",
          "name": "Semisulcospira pusilla Matsuoka & Miura, 2018",
          "rank": "SPECIES",
          "commonName": "Semisulcospira Pusilla Matsuoka & Miura, 2018",
          "lineage": "Semisulcospira",
          "subspeciesCount": 0,
          "description": "Semisulcospira pusilla Matsuoka & Miura, 2018 — a gastropoda species in the genus Semisulcospira.",
          "sourcedFrom": "generated"
        },
        {
          "id": "SP_SEMISULCOSPIRA_REINIANA",
          "name": "Semisulcospira reiniana",
          "rank": "SPECIES",
          "commonName": "Semisulcospira Reiniana",
          "lineage": "Semisulcospira",
          "subspeciesCount": 0,
          "description": "Semisulcospira reiniana — a gastropoda species in the genus Semisulcospira.",
          "sourcedFrom": "generated"
        },
        {
          "id": "SP_SEMISULCOSPIRA_RETICULATA_KAJIYAMA_HABE_1961",
          "name": "Semisulcospira reticulata Kajiyama & Habe, 1961",
          "rank": "SPECIES",
          "commonName": "Semisulcospira Reticulata Kajiyama & Habe, 1961",
          "lineage": "Semisulcospira",
          "subspeciesCount": 0,
          "description": "Semisulcospira reticulata Kajiyama & Habe, 1961 — a gastropoda species in the genus Semisulcospira.",
          "sourcedFrom": "generated"
        },
        {
          "id": "SP_SEMISULCOSPIRA_RETICULATAFORMIS_MATSUOKA_MIURA_2019",
          "name": "Semisulcospira reticulataformis Matsuoka & Miura, 2019",
          "rank": "SPECIES",
          "commonName": "Semisulcospira Reticulataformis Matsuoka & Miura, 2019",
          "lineage": "Semisulcospira",
          "subspeciesCount": 0,
          "description": "Semisulcospira reticulataformis Matsuoka & Miura, 2019 — a gastropoda species in the genus Semisulcospira.",
          "sourcedFrom": "generated"
        },
        {
          "id": "SP_SEMISULCOSPIRA_RUGOSA_N_WATANABE_NISHINO_1995",
          "name": "Semisulcospira rugosa N.Watanabe & Nishino, 1995",
          "rank": "SPECIES",
          "commonName": "Semisulcospira Rugosa N.Watanabe & Nishino, 1995",
          "lineage": "Semisulcospira",
          "subspeciesCount": 0,
          "description": "Semisulcospira rugosa N.Watanabe & Nishino, 1995 — a gastropoda species in the genus Semisulcospira.",
          "sourcedFrom": "generated"
        },
        {
          "id": "SP_SEMISULCOSPIRA_SHIRAISHIENSIS_N_WATANABE_NISHINO_1995",
          "name": "Semisulcospira shiraishiensis N.Watanabe & Nishino, 1995",
          "rank": "SPECIES",
          "commonName": "Semisulcospira Shiraishiensis N.Watanabe & Nishino, 1995",
          "lineage": "Semisulcospira",
          "subspeciesCount": 0,
          "description": "Semisulcospira shiraishiensis N.Watanabe & Nishino, 1995 — a gastropoda species in the genus Semisulcospira.",
          "sourcedFrom": "generated"
        },
        {
          "id": "SP_SEMISULCOSPIRA_SPINULIFERA_MATSUOKA_MIURA_2018",
          "name": "Semisulcospira spinulifera Matsuoka & Miura, 2018",
          "rank": "SPECIES",
          "commonName": "Semisulcospira Spinulifera Matsuoka & Miura, 2018",
          "lineage": "Semisulcospira",
          "subspeciesCount": 0,
          "description": "Semisulcospira spinulifera Matsuoka & Miura, 2018 — a gastropoda species in the genus Semisulcospira.",
          "sourcedFrom": "generated"
        },
        {
          "id": "SP_SEMISULCOSPIRA_TAGAENSIS_MATSUOKA_MIURA_2019",
          "name": "Semisulcospira tagaensis Matsuoka & Miura, 2019",
          "rank": "SPECIES",
          "commonName": "Semisulcospira Tagaensis Matsuoka & Miura, 2019",
          "lineage": "Semisulcospira",
          "subspeciesCount": 0,
          "description": "Semisulcospira tagaensis Matsuoka & Miura, 2019 — a gastropoda species in the genus Semisulcospira.",
          "sourcedFrom": "generated"
        },
        {
          "id": "SP_SEMISULCOSPIRA_TAKESHIMENSIS_N_WATANABE_NISHINO_1995",
          "name": "Semisulcospira takeshimensis N.Watanabe & Nishino, 1995",
          "rank": "SPECIES",
          "commonName": "Semisulcospira Takeshimensis N.Watanabe & Nishino, 1995",
          "lineage": "Semisulcospira",
          "subspeciesCount": 0,
          "description": "Semisulcospira takeshimensis N.Watanabe & Nishino, 1995 — a gastropoda species in the genus Semisulcospira.",
          "sourcedFrom": "generated"
        }
      ]
    },
    {
      "id": "GENUS_HUA",
      "name": "Hua",
      "rank": "GENUS",
      "description": "Hua — a genus of gastropodas.",
      "lineage": "Hua",
      "children": [
        {
          "id": "SP_HUA_ARISTARCHORUM",
          "name": "Hua aristarchorum",
          "rank": "SPECIES",
          "commonName": "Hua Aristarchorum",
          "lineage": "Hua",
          "subspeciesCount": 0,
          "description": "Hua aristarchorum — a gastropoda species in the genus Hua.",
          "sourcedFrom": "generated"
        },
        {
          "id": "SP_HUA_AUBRYANA",
          "name": "Hua aubryana",
          "rank": "SPECIES",
          "commonName": "Hua Aubryana",
          "lineage": "Hua",
          "subspeciesCount": 0,
          "description": "Hua aubryana — a gastropoda species in the genus Hua.",
          "sourcedFrom": "generated"
        },
        {
          "id": "SP_HUA_BAILLETI",
          "name": "Hua bailleti",
          "rank": "SPECIES",
          "commonName": "Hua Bailleti",
          "lineage": "Hua",
          "subspeciesCount": 0,
          "description": "Hua bailleti — a gastropoda species in the genus Hua.",
          "sourcedFrom": "generated"
        },
        {
          "id": "SP_HUA_FUNINGENSIS_L_N_DU_K_HLER_X_Y_CHEN_J_X_YANG_2019",
          "name": "Hua funingensis L.-N.Du, Köhler, X.-Y.Chen & J.-X.Yang, 2019",
          "rank": "SPECIES",
          "commonName": "Hua Funingensis L.-N.Du, KöHler, X.-Y.Chen & J.-X.Yang, 2019",
          "lineage": "Hua",
          "subspeciesCount": 0,
          "description": "Hua funingensis L.-N.Du, Köhler, X.-Y.Chen & J.-X.Yang, 2019 — a gastropoda species in the genus Hua.",
          "sourcedFrom": "generated"
        },
        {
          "id": "SP_HUA_JACQUETI",
          "name": "Hua jacqueti",
          "rank": "SPECIES",
          "commonName": "Hua Jacqueti",
          "lineage": "Hua",
          "subspeciesCount": 0,
          "description": "Hua jacqueti — a gastropoda species in the genus Hua.",
          "sourcedFrom": "generated"
        },
        {
          "id": "SP_HUA_KUNMINGENSIS_L_N_DU_K_HLER_G_H_YU_X_Y_CHEN_J_X_YANG_2019",
          "name": "Hua kunmingensis L.-N.Du, Köhler, G.-H.Yu, X.-Y.Chen & J.-X.Yang, 2019",
          "rank": "SPECIES",
          "commonName": "Hua Kunmingensis L.-N.Du, KöHler, G.-H.Yu, X.-Y.Chen & J.-X.Yang, 2019",
          "lineage": "Hua",
          "subspeciesCount": 0,
          "description": "Hua kunmingensis L.-N.Du, Köhler, G.-H.Yu, X.-Y.Chen & J.-X.Yang, 2019 — a gastropoda species in the genus Hua.",
          "sourcedFrom": "generated"
        },
        {
          "id": "SP_HUA_LIUII_L_N_DU_K_HLER_G_H_YU_X_Y_CHEN_J_X_YANG_2019",
          "name": "Hua liuii L.-N.Du, Köhler, G.-H.Yu, X.-Y.Chen & J.-X.Yang, 2019",
          "rank": "SPECIES",
          "commonName": "Hua Liuii L.-N.Du, KöHler, G.-H.Yu, X.-Y.Chen & J.-X.Yang, 2019",
          "lineage": "Hua",
          "subspeciesCount": 0,
          "description": "Hua liuii L.-N.Du, Köhler, G.-H.Yu, X.-Y.Chen & J.-X.Yang, 2019 — a gastropoda species in the genus Hua.",
          "sourcedFrom": "generated"
        },
        {
          "id": "SP_HUA_PALLENS",
          "name": "Hua pallens",
          "rank": "SPECIES",
          "commonName": "Hua Pallens",
          "lineage": "Hua",
          "subspeciesCount": 0,
          "description": "Hua pallens — a gastropoda species in the genus Hua.",
          "sourcedFrom": "generated"
        },
        {
          "id": "SP_HUA_ROTUNDATA",
          "name": "Hua rotundata",
          "rank": "SPECIES",
          "commonName": "Hua Rotundata",
          "lineage": "Hua",
          "subspeciesCount": 0,
          "description": "Hua rotundata — a gastropoda species in the genus Hua.",
          "sourcedFrom": "generated"
        },
        {
          "id": "SP_HUA_SCRUPEA",
          "name": "Hua scrupea",
          "rank": "SPECIES",
          "commonName": "Hua Scrupea",
          "lineage": "Hua",
          "subspeciesCount": 0,
          "description": "Hua scrupea — a gastropoda species in the genus Hua.",
          "sourcedFrom": "generated"
        },
        {
          "id": "SP_HUA_TCHANGSII_L_N_DU_K_HLER_G_H_YU_X_Y_CHEN_J_X_YANG_2019",
          "name": "Hua tchangsii L.-N.Du, Köhler, G.-H.Yu, X.-Y.Chen & J.-X.Yang, 2019",
          "rank": "SPECIES",
          "commonName": "Hua Tchangsii L.-N.Du, KöHler, G.-H.Yu, X.-Y.Chen & J.-X.Yang, 2019",
          "lineage": "Hua",
          "subspeciesCount": 0,
          "description": "Hua tchangsii L.-N.Du, Köhler, G.-H.Yu, X.-Y.Chen & J.-X.Yang, 2019 — a gastropoda species in the genus Hua.",
          "sourcedFrom": "generated"
        },
        {
          "id": "SP_HUA_TELONARIA",
          "name": "Hua telonaria",
          "rank": "SPECIES",
          "commonName": "Hua Telonaria",
          "lineage": "Hua",
          "subspeciesCount": 0,
          "description": "Hua telonaria — a gastropoda species in the genus Hua.",
          "sourcedFrom": "generated"
        },
        {
          "id": "SP_HUA_TEXTORIA",
          "name": "Hua textoria",
          "rank": "SPECIES",
          "commonName": "Hua Textoria",
          "lineage": "Hua",
          "subspeciesCount": 0,
          "description": "Hua textoria — a gastropoda species in the genus Hua.",
          "sourcedFrom": "generated"
        },
        {
          "id": "SP_HUA_TEXTRIX",
          "name": "Hua textrix",
          "rank": "SPECIES",
          "commonName": "Hua Textrix",
          "lineage": "Hua",
          "subspeciesCount": 0,
          "description": "Hua textrix — a gastropoda species in the genus Hua.",
          "sourcedFrom": "generated"
        },
        {
          "id": "SP_HUA_VULTUOSA",
          "name": "Hua vultuosa",
          "rank": "SPECIES",
          "commonName": "Hua Vultuosa",
          "lineage": "Hua",
          "subspeciesCount": 0,
          "description": "Hua vultuosa — a gastropoda species in the genus Hua.",
          "sourcedFrom": "generated"
        }
      ]
    },
    {
      "id": "GENUS_KOREOLEPTOXIS",
      "name": "Koreoleptoxis",
      "rank": "GENUS",
      "description": "Koreoleptoxis — a genus of gastropodas.",
      "lineage": "Koreoleptoxis",
      "children": [
        {
          "id": "SP_HUA_BICINTUS",
          "name": "Hua bicintus",
          "rank": "SPECIES",
          "commonName": "Koreoleptoxis Bicintus",
          "lineage": "Koreoleptoxis",
          "subspeciesCount": 0,
          "description": "Hua bicintus — a gastropoda species in the genus Koreoleptoxis.",
          "sourcedFrom": "generated"
        },
        {
          "id": "SP_KOREOLEPTOXIS_AMURENSIS",
          "name": "Koreoleptoxis amurensis",
          "rank": "SPECIES",
          "commonName": "Koreoleptoxis Amurensis",
          "lineage": "Koreoleptoxis",
          "subspeciesCount": 0,
          "description": "Koreoleptoxis amurensis — a gastropoda species in the genus Koreoleptoxis.",
          "sourcedFrom": "generated"
        },
        {
          "id": "SP_KOREOLEPTOXIS_DIMINUTA",
          "name": "Koreoleptoxis diminuta",
          "rank": "SPECIES",
          "commonName": "Koreoleptoxis Diminuta",
          "lineage": "Koreoleptoxis",
          "subspeciesCount": 0,
          "description": "Koreoleptoxis diminuta — a gastropoda species in the genus Koreoleptoxis.",
          "sourcedFrom": "generated"
        },
        {
          "id": "SP_KOREOLEPTOXIS_DOLICHOSTOMA",
          "name": "Koreoleptoxis dolichostoma",
          "rank": "SPECIES",
          "commonName": "Koreoleptoxis Dolichostoma",
          "lineage": "Koreoleptoxis",
          "subspeciesCount": 0,
          "description": "Koreoleptoxis dolichostoma — a gastropoda species in the genus Koreoleptoxis.",
          "sourcedFrom": "generated"
        },
        {
          "id": "SP_KOREOLEPTOXIS_FRINIANA",
          "name": "Koreoleptoxis friniana",
          "rank": "SPECIES",
          "commonName": "Koreoleptoxis Friniana",
          "lineage": "Koreoleptoxis",
          "subspeciesCount": 0,
          "description": "Koreoleptoxis friniana — a gastropoda species in the genus Koreoleptoxis.",
          "sourcedFrom": "generated"
        },
        {
          "id": "SP_KOREOLEPTOXIS_GLOBUS",
          "name": "Koreoleptoxis globus",
          "rank": "SPECIES",
          "commonName": "Koreoleptoxis Globus",
          "lineage": "Koreoleptoxis",
          "subspeciesCount": 0,
          "description": "Koreoleptoxis globus — a gastropoda species in the genus Koreoleptoxis.",
          "sourcedFrom": "generated"
        },
        {
          "id": "SP_KOREOLEPTOXIS_NODIFILA",
          "name": "Koreoleptoxis nodifila",
          "rank": "SPECIES",
          "commonName": "Koreoleptoxis Nodifila",
          "lineage": "Koreoleptoxis",
          "subspeciesCount": 0,
          "description": "Koreoleptoxis nodifila — a gastropoda species in the genus Koreoleptoxis.",
          "sourcedFrom": "generated"
        },
        {
          "id": "SP_KOREOLEPTOXIS_PACIFICANS",
          "name": "Koreoleptoxis pacificans",
          "rank": "SPECIES",
          "commonName": "Koreoleptoxis Pacificans",
          "lineage": "Koreoleptoxis",
          "subspeciesCount": 0,
          "description": "Koreoleptoxis pacificans — a gastropoda species in the genus Koreoleptoxis.",
          "sourcedFrom": "generated"
        },
        {
          "id": "SP_KOREOLEPTOXIS_TEGULATA",
          "name": "Koreoleptoxis tegulata",
          "rank": "SPECIES",
          "commonName": "Koreoleptoxis Tegulata",
          "lineage": "Koreoleptoxis",
          "subspeciesCount": 0,
          "description": "Koreoleptoxis tegulata — a gastropoda species in the genus Koreoleptoxis.",
          "sourcedFrom": "generated"
        }
      ]
    }
  ]
}
